electron/__init__.py
electron/exceptions.py
electron/messages.py
electron/server.py
electron/types.py
electron/utils.py
electron/tests/__init__.py
electron/tests/conftest.py
electron/tests/test_endpoints.py
electron/tests/test_messages.py
electron/tests/test_server.py
electron_rpc-0.0.4.dist-info/LICENSE
electron_rpc-0.0.4.dist-info/METADATA
electron_rpc-0.0.4.dist-info/WHEEL
electron_rpc-0.0.4.dist-info/top_level.txt
electron_rpc-0.0.4.dist-info/RECORD
