Metadata-Version: 2.1
Name: electron-rpc
Version: 0.0.4
Summary: Rapid RPC Framework for your Python services using Asyncio + MsgPack
Home-page: https://github.com/dvf/electron
Author: Daniel van Flymen
Author-email: vanflymen@gmail.com
License: UNKNOWN
Platform: UNKNOWN
Classifier: Programming Language :: Python :: 3
Classifier: Programming Language :: Python :: 3.7
Classifier: Programming Language :: Python :: Implementation :: CPython
Classifier: License :: OSI Approved :: MIT License
Classifier: Operating System :: OS Independent
Requires-Dist: loguru (==0.2.4)
Requires-Dist: msgpack (==0.6.0)
